w01florem/__init__.py
w01florem/main.py
w01florem/program.py
w01florem-0.1.0.dist-info/LICENSE
w01florem-0.1.0.dist-info/METADATA
w01florem-0.1.0.dist-info/WHEEL
w01florem-0.1.0.dist-info/top_level.txt
w01florem-0.1.0.dist-info/RECORD
