Metadata-Version: 2.1
Name: w01florem
Version: 0.1.0
Summary: A lorem ipsum creator with the special feature of  creating multiple files with different names and contents in different  folders.
Home-page: https://github.com/w01fdev/w01florem
Author: w01f
Author-email: w01f@w01f.dev
License: GPL-3.0
Platform: UNKNOWN
Classifier: Development Status :: 3 - Alpha
Classifier: Programming Language :: Python :: 3.3
Classifier: Programming Language :: Python :: 3.4
Classifier: Programming Language :: Python :: 3.5
Classifier: Programming Language :: Python :: 3.6
Classifier: Programming Language :: Python :: 3.7
Classifier: Programming Language :: Python :: 3.8
Classifier: Programming Language :: Python :: 3.9
Requires-Python: >=3.3
